wgcpy/__init__.py
wgcpy/config.py
wgcpy/main.py
wgcpy/bins/__init__.py
wgcpy/bins/chi_merge.py
wgcpy/bins/cut_bins.py
wgcpy/featureSelector/__init__.py
wgcpy/featureSelector/cal_iv_psi.py
wgcpy/featureSelector/selector.py
wgcpy/model/__init__.py
wgcpy/model/dz_eval.py
wgcpy/model/gen_model.py
wgcpy/model/gen_pmml_model.py
wgcpy/preprocessing/__init__.py
wgcpy/preprocessing/data_dectection.py
wgcpy/preprocessing/eda.py
wgcpy/utils/__init__.py
wgcpy/utils/ext_fn.py
wgcpy-1.0.0.dist-info/LICENSE
wgcpy-1.0.0.dist-info/METADATA
wgcpy-1.0.0.dist-info/WHEEL
wgcpy-1.0.0.dist-info/top_level.txt
wgcpy-1.0.0.dist-info/zip-safe
wgcpy-1.0.0.dist-info/RECORD
